LICENSE
MANIFEST.in
README.md
pyproject.toml
setup.py
jcloud/__init__.py
jcloud/__main__.py
jcloud/api.py
jcloud/constants.py
jcloud/deployment.py
jcloud/env_helper.py
jcloud/flow.py
jcloud/helper.py
jcloud/normalize.py
jcloud.egg-info/PKG-INFO
jcloud.egg-info/SOURCES.txt
jcloud.egg-info/dependency_links.txt
jcloud.egg-info/entry_points.txt
jcloud.egg-info/not-zip-safe
jcloud.egg-info/requires.txt
jcloud.egg-info/top_level.txt
jcloud/parsers/__init__.py
jcloud/parsers/base.py
jcloud/parsers/create.py
jcloud/parsers/custom_actions.py
jcloud/parsers/deploy.py
jcloud/parsers/get.py
jcloud/parsers/helper.py
jcloud/parsers/list.py
jcloud/parsers/logs.py
jcloud/parsers/normalize.py
jcloud/parsers/remove.py
jcloud/parsers/status.py
jcloud/parsers/update.py
jcloud/resources/project-template/.env
jcloud/resources/project-template/flow.yml
jcloud/resources/project-template/executor1/config.yml
jcloud/resources/project-template/executor1/executor.py
jcloud/resources/project-template/executor1/requirements.txt